ednaml/__init__.py
ednaml/backbones/__init__.py
ednaml/backbones/multibranchresnet.py
ednaml/backbones/resnet.py
ednaml/backbones/shufflenet.py
ednaml/config/ConfigDefaults.py
ednaml/config/EdnaMLConfig.py
ednaml/config/ExecutionConfig.py
ednaml/config/ExecutionDatareaderConfig.py
ednaml/config/LoggingConfig.py
ednaml/config/LossConfig.py
ednaml/config/ModelConfig.py
ednaml/config/OptimizerConfig.py
ednaml/config/OptimizerListConfig.py
ednaml/config/SaveConfig.py
ednaml/config/SchedulerConfig.py
ednaml/config/TransformationConfig.py
ednaml/config/__init__.py
ednaml/core/EdnaML.py
ednaml/core/__init__.py
ednaml/crawlers/CUB200_2011DataCrawler.py
ednaml/crawlers/Cars196DataCrawler.py
ednaml/crawlers/ClassedCrawler.py
ednaml/crawlers/CoLabelCompCarsCrawler.py
ednaml/crawlers/CoLabelIntegratedDatasetCrawler.py
ednaml/crawlers/CoLabelVehicleColorCrawler.py
ednaml/crawlers/MTMCDataCrawler.py
ednaml/crawlers/Market1501DataCrawler.py
ednaml/crawlers/SUNDataCrawler.py
ednaml/crawlers/VRICDataCrawler.py
ednaml/crawlers/VeRiDataCrawler.py
ednaml/crawlers/VehicleIDDataCrawler.py
ednaml/crawlers/__init__.py
ednaml/datareaders/CompCars.py
ednaml/datareaders/VeRi.py
ednaml/datareaders/VehicleColor.py
ednaml/datareaders/VehicleID.py
ednaml/datareaders/__init__.py
ednaml/exceptions/__init__.py
ednaml/generators/ClassificationGenerator.py
ednaml/generators/CoLabelDeployGenerator.py
ednaml/generators/CoLabelIntegratedDatasetGenerator.py
ednaml/generators/MultiClassificationGenerator.py
ednaml/generators/__init__.py
ednaml/loss/CenterLoss.py
ednaml/loss/ClusterLoss.py
ednaml/loss/CompactContrastiveLoss.py
ednaml/loss/ContrastiveLoss.py
ednaml/loss/MarginLoss.py
ednaml/loss/ProxyNCA.py
ednaml/loss/SoftmaxLabelSmooth.py
ednaml/loss/SoftmaxLogitsLoss.py
ednaml/loss/TripletLoss.py
ednaml/loss/__init__.py
ednaml/loss/builders/ClassificationLossBuilder.py
ednaml/loss/builders/__init__.py
ednaml/models/ClassificationResnet.py
ednaml/models/ModelAbstract.py
ednaml/models/MultiBranchResnet.py
ednaml-0.1.4.dist-info/LICENSE
ednaml-0.1.4.dist-info/METADATA
ednaml-0.1.4.dist-info/WHEEL
ednaml-0.1.4.dist-info/top_level.txt
ednaml-0.1.4.dist-info/RECORD
