Metadata-Version: 2.1
Name: ednaml
Version: 0.1.4
Summary: A framework running and tracking ML experiments
Home-page: https://github.com/asuprem/GLAMOR
Author: Abhijit Suprem
Author-email: asuprem@gatech.edu
Maintainer: Abhijit Suprem
Maintainer-email: asuprem@gatech.edu
License: Apache 2.0
Project-URL: Documentation, https://github.com/asuprem/GLAMOR
Project-URL: Code, https://github.com/asuprem/GLAMOR
Project-URL: Issue tracker, https://github.com/asuprem/GLAMOR/issues
Keywords: deep learning,pytorch,AI
Platform: UNKNOWN
Classifier: Development Status :: 2 - Pre-Alpha
Classifier: Environment :: Console
Classifier: Environment :: GPU :: NVIDIA CUDA :: 11.0
Classifier: Intended Audience :: Developers
Classifier: License :: OSI Approved :: Apache Software License
Classifier: Operating System :: OS Independent
Classifier: Programming Language :: Python
Classifier: Topic :: Software Development :: Libraries :: Application Frameworks
Classifier: Topic :: Software Development :: Libraries :: Python Modules
Requires-Python: >=3.7
License-File: LICENSE
Requires-Dist: scikit-learn (>=1.0.2)
Requires-Dist: torch (>=1.10.*)
Requires-Dist: torchinfo (>=1.6.5)
Requires-Dist: torchvision (>=0.11.*)
Requires-Dist: Pillow (>=9.0.*)
Requires-Dist: tqdm (>=4.63.*)
